{
  "db_name": "PostgreSQL",
  "query": "UPDATE users SET verification_code = $1, code_expires_at = $2 WHERE username = $3 RETURNING email, verification_code",
  "describe": {
    "columns": [
      {
        "ordinal": 0,
        "name": "email",
        "type_info": "Text"
      },
      {
        "ordinal": 1,
        "name": "verification_code",
        "type_info": "Varchar"
      }
    ],
    "parameters": {
      "Left": [
        "Varchar",
        "Timestamptz",
        "Text"
      ]
    },
    "nullable": [
      false,
      true
    ]
  },
  "hash": "1a556b27a871c55f0c79f8237c86c4920a6418406988d8c98e5bedbfe2c2b85b"
}
